macsylib/__init__.py
macsylib/cluster.py
macsylib/config.py
macsylib/database.py
macsylib/definition_parser.py
macsylib/error.py
macsylib/gene.py
macsylib/hit.py
macsylib/io.py
macsylib/licenses.py
macsylib/metadata.py
macsylib/model.py
macsylib/model_conf_parser.py
macsylib/model_package.py
macsylib/profile.py
macsylib/registries.py
macsylib/report.py
macsylib/search_genes.py
macsylib/search_systems.py
macsylib/serialization.py
macsylib/solution.py
macsylib/system.py
macsylib/utils.py
macsylib/data/__init__.py
macsylib/data/model.xsd
macsylib/data/model_conf.xsd
macsylib/data/pre-push
macsylib/scripts/__init__.py
macsylib/scripts/macsydata.py
macsylib/scripts/macsyprofile.py
macsylib-1.0.4.dist-info/licenses/COPYING
macsylib-1.0.4.dist-info/METADATA
macsylib-1.0.4.dist-info/WHEEL
macsylib-1.0.4.dist-info/entry_points.txt
macsylib-1.0.4.dist-info/top_level.txt
macsylib-1.0.4.dist-info/RECORD
