Metadata-Version: 2.4
Name: MacSyLib
Version: 1.0.4
Summary: MacSyLib: Python library that help to detect of macromolecular, systems genetic pathways… in prokaryotes protein datasets using systems modelling and similarity search.
Author-email: Sophie Abby <sophie.abby@univ-grenoble-alpes.fr>, Bertrand Neron <bneron@pasteur.fr>
Maintainer-email: Bertrand Neron <bneron@pasteur.fr>
License-Expression: GPL-3.0-or-later
Project-URL: Homepage, https://github.com/gem-pasteur/macsylib/
Project-URL: Documentation, https://macsylib.readthedocs.io/en/latest/
Project-URL: Repository, https://github.com/gem-pasteur/macsylib/
Project-URL: Issues, https://github.com/gem-pasteur/macsylib/issues
Project-URL: Changelog, https://macsylib.readthedocs.io/en/latest/user_guide/new.html
Keywords: science,research,bioinformatic,microbiology,genomic,prokaryote,functional gene annotation
Classifier: Programming Language :: Python :: 3
Classifier: Programming Language :: Python :: 3.10
Classifier: Programming Language :: Python :: 3.11
Classifier: Programming Language :: Python :: 3.12
Classifier: Programming Language :: Python :: 3.13
Classifier: Programming Language :: Python :: 3.14
Classifier: Operating System :: POSIX
Classifier: Environment :: Console
Classifier: Development Status :: 5 - Production/Stable
Classifier: Intended Audience :: Science/Research
Classifier: Topic :: Scientific/Engineering :: Bio-Informatics
Requires-Python: >=3.10
License-File: COPYING
Requires-Dist: colorlog>=4.0.2
Requires-Dist: PyYAML>=5.1.1
Requires-Dist: packaging>=18.0
Requires-Dist: networkx>=2.4
Requires-Dist: pandas>=1.03
Requires-Dist: colorama>=0.4.4
Requires-Dist: certifi
Provides-Extra: model
Requires-Dist: GitPython; extra == "model"
Requires-Dist: lxml; extra == "model"
Provides-Extra: dev
Requires-Dist: macsylib[model]; extra == "dev"
Requires-Dist: sphinx; extra == "dev"
Requires-Dist: sphinx_rtd_theme; extra == "dev"
Requires-Dist: sphinx-autodoc-typehints; extra == "dev"
Requires-Dist: sphinxcontrib-svg2pdfconverter; extra == "dev"
Requires-Dist: coverage[toml]; extra == "dev"
Requires-Dist: build; extra == "dev"
Requires-Dist: ruff; extra == "dev"
Requires-Dist: pre-commit; extra == "dev"
Dynamic: license-file
